mcp_jira_tools/__init__.py
mcp_jira_tools/config.py
mcp_jira_tools/jira_client.py
mcp_jira_tools/server.py
tests/__init__.py
tests/mock_jira_server.py
tests/test_mcp_jira_tools.py
mcp_jira_tools-0.1.1.dist-info/METADATA
mcp_jira_tools-0.1.1.dist-info/WHEEL
mcp_jira_tools-0.1.1.dist-info/entry_points.txt
mcp_jira_tools-0.1.1.dist-info/top_level.txt
mcp_jira_tools-0.1.1.dist-info/RECORD
