Metadata-Version: 2.4
Name: mcp-jira-tools
Version: 0.1.1
Summary: MCP server for Jira integration
Home-page: https://github.com/yourusername/mcp-jira-tools
Author: Your Name
Author-email: your@email.com
Classifier: Programming Language :: Python :: 3
Classifier: License :: OSI Approved :: MIT License
Classifier: Operating System :: OS Independent
Requires-Python: >=3.8
Requires-Dist: fastmcp
Requires-Dist: jira
Requires-Dist: python-dotenv
Dynamic: author
Dynamic: author-email
Dynamic: classifier
Dynamic: description
Dynamic: description-content-type
Dynamic: home-page
Dynamic: requires-dist
Dynamic: requires-python
Dynamic: summary
